{"/BN-and-MRF/": "6", "/Spectral-Analysis-4/": "5", "/VAE/": "5", "/machine learning/Gaussian_Process_Regression/": "5", "/\ucd5c\ub2e8\uacbd\ub85c\uc54c\uace0\ub9ac\uc998/": "4", "/KStest/": "4", "/Markov-Random-Field/": "4", "/Spatial-Hierarchical-Model/": "4", "/Universal-Approximation-Theorem/": "4", "/machine learning/Expectation_Propagation/": "2", "/machine learning/Laplace_Approximation_Binary_GP_Classifier/": "2", "/page2/": "4", "/statistics/MM_algorithm/": "4", "/ATE-estimation/": "3", "/Disease-mapping/": "3", "/Jekyll-Tag-\uae30\ub2a5-\ucd94\uac00\ud558\uae30/": "1", "/Spectral-Analysis-3/": "3", "/Spectral-Analysis-5/": "3", "/bayesian/BDA_(2)/": "3", "/causal inference/Causal_Inference_(6)/": "3", "/deep learning/AlexNet/": "3", "/deep learning/Optimization/": "1", "/deep learning/simpe_nn_with_tf/": "3", "/machine learning/Gaussian_Process/": "3", "/machine learning/Gaussian_Process_Classification/": "2", "/machine learning/Gradient_Boosting/": "3", "/machine learning/Robust_PCA/": "3", "/machine learning/Support_Vector_Machine/": "3", "/machine learning/kernelpca/": "3", "/mathematics/\uc2e4\ud574\uc11d\ud5592/": "3", "/page3/": "3", "/\ud504\ub85c\uadf8\ub798\uba38\uc2a4-181187/": "1", "/Average-Treatment-Effect/": "2", "/Bayesian-Causal-Inference/": "2", "/Jupyter-convert/": "2", "/Spectral-Analysis-1/": "2", "/Spectral-Analysis-2/": "2", "/bayesian/BDA_(1)/": "2", "/causal inference/Causal_Inference_(2)/": "2", "/causal inference/Causal_Inference_(5)/": "2", "/deep learning/Backpropagation/": "2", "/deep learning/CNN/": "2", "/linear model/Linear_Mixed_Effect_Model/": "2", "/linear model/Partial_Regression/": "2", "/linear model/expansion1/": "2", "/linear model/lda1/": "2", "/machine learning/An_Overview_of_Statistical_Learning/": "2", "/machine learning/Model_Assessment/": "2", "/machine learning/Splines/": "2", "/machine learning/Support_Vector_Regression/": "2", "/machine learning/boosting/": "2", "/machine learning/kernel1/": "2", "/machine learning/kernel2/": "2", "/mathematics/\uc2e4\ud574\uc11d\ud55910/": "2", "/project/\ub530\ub989\uc774_AutoML/": "2", "/project/\uc81c1\ud68c_\uc9c0\uc5ed\uce58\uc548\ub370\uc774\ud130\ubd84\uc11d\uacbd\uc9c4\ub300\ud68c_\uacf5\ubaa8\uc804_\ud6c4\uae30/": "2", "/recommender system/Recommeder_Systems/": "2", "/resume/": "2", "/time series/Spectral_Density/": "2", "/\uc774\uc9c4\ud2b8\ub9ac/": "1", "/\ud504\ub85c\uadf8\ub798\uba38\uc2a4-12945/": "1", "/\ud504\ub85c\uadf8\ub798\uba38\uc2a4-169198/": "1", "/\ud504\ub85c\uadf8\ub798\uba38\uc2a4-42892/": "1", "/\ud504\ub85c\uadf8\ub798\uba38\uc2a4-86971/": "1", "/\ud504\ub85c\uadf8\ub798\uba38\uc2a4-92343/": "1", "/DAG-GNN/": "1", "/Monte-Carlo-Sampling/": "1", "/Randomized-Experiment/": "1", "/Variational-Inference/": "1", "/baekjoonhub/": "1", "/causal inference/Causal_Inference_(1)/": "1", "/causal inference/Causal_Inference_(3)/": "1", "/causal inference/Causal_Inference_(4)/": "1", "/causal inference/Probabilistic_Graphical_Models/": "1", "/computer science/REST_API/": "1", "/deep learning/0709_KISS_Summer_school_DL_Lecture/": "1", "/deep learning/LSTM-FCN/": "1", "/deep learning/Multivariate_LSTM-FCN/": "1", "/deep learning/Neural_Network/": "1", "/deep learning/Regularization_on_DL/": "1", "/etc/itreview1/": "1", "/etc/itreview2/": "1", "/linear model/lda2/": "1", "/linear model/linearreg1/": "1", "/linear model/linearreg2/": "1", "/machine learning/RandomForest/": "1", "/machine learning/kernel3/": "1", "/machine learning/Cross_Validation/": "1", "/machine learning/Mixture_Model/": "1", "/machine learning/Self-Organizing_Map/": "1", "/machine learning/Tree/": "1", "/machine learning/tSNE/": "1", "/math/\uc2e4\ud574\uc11d\ud55910/": "1", "/math/\uc2e4\ud574\uc11d\ud55912/": "1", "/math/\uc2e4\ud574\uc11d\ud55914/": "1", "/math/\uc2e4\ud574\uc11d\ud55915/": "1", "/mathematics/\uc2e4\ud574\uc11d\ud5591/": "1", "/mathematics/\uc2e4\ud574\uc11d\ud55911/": "1", "/mathematics/\uc2e4\ud574\uc11d\ud5595/": "1", "/mathematics/\uc2e4\ud574\uc11d\ud55913/": "1", "/opinion/Radical_empiricism/": "1", "/page11/": "1", "/page24/": "1", "/page4/": "1", "/page5/": "1", "/page6/": "1", "/probability theory/Conditional_Expectations/": "1", "/probability theory/prob_1/": "1", "/project/\ub530\ub989\uc774_Linear/": "1", "/project/\ub530\ub989\uc774_SVM/": "1", "/project/\ub530\ub989\uc774_shrinkage/": "1", "/project/\ub530\ub989\uc774_transform/": "1", "/project/\uacf5\ubaa8\uc804_\ud6c4\uae30/": "1", "/recommender systems/Recommeder_Systems/": "1", "/statistics/MCMC/": "1", "/statistics/Spatial-Stat-3/": "1", "/time series/State-Space_Model/": "1", "/\ud504\ub85c\uadf8\ub798\uba38\uc2a4-72413/": "1"}